strands_agentcore_tools/__init__.py
strands_agentcore_tools/agents.py
strands_agentcore_tools/configure.py
strands_agentcore_tools/identity.py
strands_agentcore_tools/invoke.py
strands_agentcore_tools/launch.py
strands_agentcore_tools/logs.py
strands_agentcore_tools/memory.py
strands_agentcore_tools/session.py
strands_agentcore_tools/status.py
strands_agentcore_tools-0.1.2.dist-info/licenses/LICENSE
strands_agentcore_tools-0.1.2.dist-info/METADATA
strands_agentcore_tools-0.1.2.dist-info/WHEEL
strands_agentcore_tools-0.1.2.dist-info/top_level.txt
strands_agentcore_tools-0.1.2.dist-info/RECORD
