Metadata-Version: 2.4
Name: strands-agentcore-tools
Version: 0.1.2
Summary: Strands tools for AWS Bedrock AgentCore lifecycle management
Home-page: https://github.com/cagataycali/strands-agentcore-tools
Author: Cagatay Cali
Author-email: Cagatay Cali <cagataycali@icloud.com>
License: MIT
Project-URL: Homepage, https://github.com/cagataycali/strands-agentcore-tools
Project-URL: Documentation, https://github.com/cagataycali/strands-agentcore-tools
Project-URL: Repository, https://github.com/cagataycali/strands-agentcore-tools
Project-URL: Bug Tracker, https://github.com/cagataycali/strands-agentcore-tools/issues
Keywords: aws,bedrock,agentcore,strands,ai,agents,tools
Classifier: Development Status :: 3 - Alpha
Classifier: Intended Audience :: Developers
Classifier: License :: OSI Approved :: MIT License
Classifier: Programming Language :: Python :: 3
Classifier: Programming Language :: Python :: 3.10
Classifier: Programming Language :: Python :: 3.11
Classifier: Programming Language :: Python :: 3.12
Classifier: Programming Language :: Python :: 3.13
Classifier: Programming Language :: Python :: 3.14
Classifier: Topic :: Software Development :: Libraries :: Python Modules
Classifier: Topic :: Scientific/Engineering :: Artificial Intelligence
Requires-Python: >=3.10
License-File: LICENSE
Requires-Dist: bedrock-agentcore
Requires-Dist: strands-agents
Requires-Dist: strands-agents-tools
Requires-Dist: pyyaml
Provides-Extra: dev
Requires-Dist: mypy>=1.8.0; extra == "dev"
Requires-Dist: black>=24.0.0; extra == "dev"
Requires-Dist: types-PyYAML; extra == "dev"
Requires-Dist: pytest>=7.4.0; extra == "dev"
Requires-Dist: pytest-asyncio>=0.21.0; extra == "dev"
Requires-Dist: ruff>=0.1.0; extra == "dev"
Dynamic: author
Dynamic: home-page
Dynamic: license-file
Dynamic: requires-python
